README.rst
setup.py
cantal/__init__.py
cantal/collection.py
cantal/collection.pyi
cantal/const.py
cantal/core.py
cantal/core.pyi
cantal/counters.py
cantal/counters.pyi
cantal/fork.py
cantal/fork.pyi
cantal/levels.py
cantal/levels.pyi
cantal/py.typed
cantal/py2_compat.py
cantal/py2_compat.pyi
cantal/req.py
cantal/req.pyi
cantal/simple_state.py
cantal/simple_state.pyi
cantal.egg-info/PKG-INFO
cantal.egg-info/SOURCES.txt
cantal.egg-info/dependency_links.txt
cantal.egg-info/top_level.txt